robotics_sympy/__init__.py
robotics_sympy-1.0.0.dist-info/METADATA
robotics_sympy-1.0.0.dist-info/WHEEL
robotics_sympy-1.0.0.dist-info/top_level.txt
robotics_sympy-1.0.0.dist-info/RECORD
