Metadata-Version: 2.1
Name: robotics-sympy
Version: 1.0.0
Summary: package for symbolic robot kinematics analysis using sympy
Home-page: https://github.com/ryanGT/robotics_sympy
Author: Ryan Krauss
Author-email: ryanwkrauss@gmail.com
License: UNKNOWN
Platform: UNKNOWN
Classifier: Programming Language :: Python :: 3
Classifier: License :: OSI Approved :: MIT License
Classifier: Operating System :: OS Independent
